duanbima/__init__.py
duanbima/anbima_holidays.txt
duanbima/duanbima.py
duanbima-2.0.dist-info/METADATA
duanbima-2.0.dist-info/WHEEL
duanbima-2.0.dist-info/top_level.txt
duanbima-2.0.dist-info/RECORD
