Metadata-Version: 2.4
Name: duanbima
Version: 2.0
Summary: Biblioteca Python para manipulação de datas úteis com base no calendário ANBIMA.
Author: Lucas Soares
Author-email: lcs-soares@hotmail.com
Requires-Python: >=3.7
Dynamic: author
Dynamic: author-email
Dynamic: description
Dynamic: description-content-type
Dynamic: requires-python
Dynamic: summary
